django_context_decorator.py
django_context_decorator-1.6.0.dist-info/METADATA
django_context_decorator-1.6.0.dist-info/WHEEL
django_context_decorator-1.6.0.dist-info/top_level.txt
django_context_decorator-1.6.0.dist-info/RECORD
