Metadata-Version: 2.1
Name: django-context-decorator
Version: 1.6.0
Summary: A context decorator for Django views
Home-page: https://github.com/rixx/django-context-decorator
Author: Tobias Kunze
Author-email: r@rixx.de
License: Apache License 2.0
Keywords: django context templates
Platform: UNKNOWN
Classifier: Development Status :: 5 - Production/Stable
Classifier: Intended Audience :: Developers
Classifier: Framework :: Django
Classifier: Programming Language :: Python :: 3.6
Classifier: Programming Language :: Python :: 3.7
Classifier: License :: OSI Approved
Classifier: License :: OSI Approved :: Apache Software License
Requires-Python: >=3.6
